{"type": "FeatureCollection", "name": "cementerio_general", "crs": {"type": "name", "properties": {"name": "urn:ogc:def:crs:OGC:1.3:CRS84"}}, "features": [{"type": "Feature", "properties": {"name": "Cementerio General de Santiago", "district": "Recoleta, Santiago, Chile", "founded": 1821, "lat": -33.418, "lon": -70.6501, "kind": "main_pedestrian_entrance", "address": "Profesor Alberto Zañartu 951, Recoleta", "label": "Main pedestrian entrance (Profesor Alberto Zañartu 951, Recoleta)"}, "geometry": {"type": "Point", "coordinates": [-70.6501, -33.418]}}]}